{
  "taskId": "decompose-2625-260418-095233",
  "state": "running",
  "stages": {
    "taskify": {
      "state": "completed",
      "completedAt": "2026-04-18T09:57:31.373Z",
      "retries": 0,
      "outputFile": "task.json",
      "promptTokens": 1675
    },
    "plan": {
      "state": "completed",
      "retries": 0
    },
    "build": {
      "state": "completed",
      "completedAt": "2026-04-18T09:59:16.078Z",
      "retries": 0,
      "promptTokens": 6151
    },
    "verify": {
      "state": "completed",
      "completedAt": "2026-04-18T10:00:37.357Z",
      "retries": 0
    },
    "review": {
      "state": "completed",
      "retries": 0
    },
    "review-fix": {
      "state": "completed",
      "retries": 0
    },
    "ship": {
      "state": "running",
      "startedAt": "2026-04-18T10:00:37.359Z",
      "retries": 0
    }
  },
  "createdAt": "2026-04-18T09:53:53.040Z",
  "updatedAt": "2026-04-18T10:00:37.359Z",
  "sessions": {
    "explore": "0a6de050-5b59-4732-a7b6-4050d4c583a9",
    "build": "17f6027d-a7be-45bd-8840-2910a33af949"
  }
}