{
  "taskId": "hotfix-1552-260410-105603",
  "state": "running",
  "stages": {
    "taskify": {
      "state": "completed",
      "retries": 0
    },
    "plan": {
      "state": "completed",
      "retries": 0
    },
    "build": {
      "state": "completed",
      "completedAt": "2026-04-10T11:10:29.886Z",
      "retries": 0,
      "promptTokens": 5935
    },
    "verify": {
      "state": "completed",
      "completedAt": "2026-04-10T11:10:57.739Z",
      "retries": 0
    },
    "review": {
      "state": "completed",
      "retries": 0
    },
    "review-fix": {
      "state": "completed",
      "retries": 0
    },
    "ship": {
      "state": "running",
      "startedAt": "2026-04-10T11:10:57.741Z",
      "retries": 0
    }
  },
  "createdAt": "2026-04-10T10:57:49.426Z",
  "updatedAt": "2026-04-10T11:10:57.741Z",
  "sessions": {
    "build": "81812258-b1a3-4299-9c54-17c88ceba110"
  }
}