{
  "id": "ep_stage_diary_003",
  "runId": "2405-260417-234631",
  "source": "stage_diary",
  "taskId": "2405-260417-234631",
  "createdAt": "2026-04-18T00:00:43.452Z",
  "rawContent": "{\"stage\":\"review-fix\",\"insights\":[{\"kind\":\"gotcha\",\"text\":\"The agent updated skill documentation files instead of writing the required implementation. No actual code was committed.\",\"scope\":\"pipeline/execution\"},{\"kind\":\"gotcha\",\"text\":\"Plan file could not be written to disk due to missing Write tool permission — this blocked plan-phase progression.\",\"scope\":\"pipeline/permissions\"},{\"kind\":\"lesson\",\"text\":\"No src/middleware/ directory exists in this repository; a new directory would need to be created as part of the implementation.\",\"scope\":\"src/middleware\"}]}",
  "extractedNodeIds": [],
  "linkedFiles": [],
  "metadata": {
    "stage": "review-fix"
  }
}