{
  "taskId": "965-260409-191525",
  "state": "running",
  "stages": {
    "taskify": {
      "state": "completed",
      "completedAt": "2026-04-09T19:18:22.668Z",
      "retries": 0,
      "outputFile": "task.json",
      "promptTokens": 1722
    },
    "plan": {
      "state": "completed",
      "retries": 0
    },
    "build": {
      "state": "completed",
      "completedAt": "2026-04-09T19:22:02.094Z",
      "retries": 0,
      "promptTokens": 5295
    },
    "verify": {
      "state": "completed",
      "completedAt": "2026-04-09T19:23:37.023Z",
      "retries": 0
    },
    "review": {
      "state": "completed",
      "retries": 0
    },
    "review-fix": {
      "state": "completed",
      "retries": 0
    },
    "ship": {
      "state": "running",
      "startedAt": "2026-04-09T19:23:37.026Z",
      "retries": 0
    }
  },
  "createdAt": "2026-04-09T19:17:17.219Z",
  "updatedAt": "2026-04-09T19:23:37.026Z",
  "sessions": {
    "explore": "42dab609-49ab-4f5d-89f4-b640f65cf7c2",
    "build": "747fe286-21eb-447e-9aa8-98d18f7bd6c9"
  }
}