{
  "taskId": "decompose-1717-260410-141221",
  "state": "running",
  "stages": {
    "taskify": {
      "state": "completed",
      "completedAt": "2026-04-10T14:15:17.443Z",
      "retries": 0,
      "outputFile": "task.json",
      "promptTokens": 1846
    },
    "plan": {
      "state": "completed",
      "retries": 0
    },
    "build": {
      "state": "running",
      "startedAt": "2026-04-10T14:15:22.688Z",
      "retries": 0
    },
    "verify": {
      "state": "pending",
      "retries": 0
    },
    "review": {
      "state": "pending",
      "retries": 0
    },
    "review-fix": {
      "state": "pending",
      "retries": 0
    },
    "ship": {
      "state": "pending",
      "retries": 0
    }
  },
  "createdAt": "2026-04-10T14:14:08.609Z",
  "updatedAt": "2026-04-10T14:15:22.688Z",
  "sessions": {
    "explore": "a20ae9a4-6e2a-49ed-b473-668ab7196cbd"
  }
}