{
  "taskId": "2302-260417-184424",
  "state": "running",
  "stages": {
    "taskify": {
      "state": "completed",
      "completedAt": "2026-04-17T19:01:58.677Z",
      "retries": 1,
      "outputFile": "task.json",
      "promptTokens": 1619
    },
    "plan": {
      "state": "completed",
      "retries": 0
    },
    "build": {
      "state": "running",
      "startedAt": "2026-04-17T19:02:02.853Z",
      "retries": 0
    },
    "verify": {
      "state": "pending",
      "retries": 0
    },
    "review": {
      "state": "pending",
      "retries": 0
    },
    "review-fix": {
      "state": "pending",
      "retries": 0
    },
    "ship": {
      "state": "pending",
      "retries": 0
    }
  },
  "createdAt": "2026-04-17T18:51:54.331Z",
  "updatedAt": "2026-04-17T19:02:02.853Z",
  "sessions": {
    "explore": "107f05b1-aa37-410a-98e1-28740755e415"
  }
}