{
  "taskId": "268-260401-211658",
  "state": "running",
  "stages": {
    "taskify": {
      "state": "pending",
      "retries": 0
    },
    "plan": {
      "state": "pending",
      "retries": 0
    },
    "build": {
      "state": "completed",
      "completedAt": "2026-04-01T22:25:44.040Z",
      "retries": 0
    },
    "verify": {
      "state": "completed",
      "completedAt": "2026-04-01T22:26:48.194Z",
      "retries": 0
    },
    "review": {
      "state": "completed",
      "completedAt": "2026-04-01T22:29:39.980Z",
      "retries": 1,
      "outputFile": "review.md"
    },
    "review-fix": {
      "state": "running",
      "startedAt": "2026-04-01T22:29:39.981Z",
      "retries": 0
    },
    "ship": {
      "state": "pending",
      "retries": 0
    }
  },
  "createdAt": "2026-04-01T22:12:07.798Z",
  "updatedAt": "2026-04-01T22:29:39.981Z",
  "sessions": {
    "build": "f335d14a-a3fa-4dc4-b89a-acbeeb809631",
    "review": "6bd71a47-7fb9-4044-ae8a-aca59503c645"
  }
}